FMS/fsm_mascota.v
module fsm_mascota (clk,reset,A,B,C,output1,output2);
    input  clk;
    input  reset;
    input  A;       // Entrada para transición de estados
    input  B;       // Entrada para modificar variable en el estado actual
    input  C;         // Nueva entrada para transición de estados en el sentido contrario
    //salidas
    output reg [7:0] output1;  
    output reg [3:0] output2;


    parameter S0=0;
    parameter S1=1;
    parameter S2=2;
    parameter S3=3;
    parameter S4=4;

    reg [0:2] state_t, current_state, next_state;
    
    reg [3:0] var_S0, var_S1, var_S2, var_S3, var_S4;

    // Registro de estado
    always @(posedge clk or posedge reset) begin
        if (reset)
            current_state <= S0;
        else
            current_state <= next_state;
    end

    // Lógica combinacional para transiciones de estado 1 sentido
/*     always @(posedge clk) begin
        case (current_state)
            S0: next_state = A ? S1 : S0;
            S1: next_state = A ? S2 : S1;
            S2: next_state = A ? S3 : S2;
            S3: next_state = A ? S4 : S3;
            S4: next_state = A ? S0 : S4;
            default: next_state = S0;
        endcase
    end */

    // Lógica combinacional para determinar el siguiente estado
    always @(posedge clk) begin
        case (current_state)
            S0: next_state = A ? S1 : (C ? S4 : S0);  // Cambia a S4 si C está activo
            S1: next_state = A ? S2 : (C ? S0 : S1);  // Cambia a S0 si C está activo
            S2: next_state = A ? S3 : (C ? S1 : S2);  // Cambia a S1 si C está activo
            S3: next_state = A ? S4 : (C ? S2 : S3);  // Cambia a S2 si C está activo
            S4: next_state = A ? S0 : (C ? S3 : S4);  // Cambia a S3 si C está activo
            default: next_state = S0;  // Valor por defecto en caso de un estado no definido
        endcase
    end


    // Modificación de variables por estado
    always @(posedge clk or posedge reset) begin
        if (reset) begin
            var_S0 <= 8'b0;
            var_S1 <= 8'b0;
            var_S2 <= 8'b0;
            var_S3 <= 8'b0;
            var_S4 <= 8'b0;
        end
        else if (B) begin
            case (current_state)
                S0: var_S0 <= var_S0 + 1;
                S1: var_S1 <= var_S1 + 1;
                S2: var_S2 <= var_S2 + 1;
                S3: var_S3 <= var_S3 + 1;
                S4: var_S4 <= var_S4 + 1;
            endcase
        end
    end

    // Lógica para las salidas
    always @(*)begin
        case (current_state)
            S0: begin
                output1 = var_S0; 
                output2 = S0;
            end
            S1: begin
                output1 = var_S1;
                output2 = S1;
            end
            S2: begin
                output1 = var_S2;
                output2 = S2;
            end
            S3: begin
                output1 = var_S3; 
                output2 = S3;
            end
            S4: begin
                output1 = var_S4;
                output2 = S4;
            end
            //default: output1 = 8'b1;
        endcase
    end


endmodule

FMS/tb_fsm_mascota.v
`include "fsm_mascota.v"

`timescale 1ns / 1ps
module tb_fsm_mascota;

    // Declaración de señales para la FSM
    reg clk;
    reg reset;
    reg A;
    reg B;
    reg C;
    wire [7:0] output1;
    wire [3:0] output2;

    // Instanciación de la FSM
    fsm_mascota uut (.clk(clk),  .reset(reset), .A(A), .B(B), .C(C), .output1(output1), .output2(output2));

    // Generación del reloj (clock)
    always #5 clk = ~clk;
    // Procedimiento inicial para configurar y ejecutar las pruebas
    initial begin
        // Inicialización de las señales
        clk = 0;
        reset = 0;
        A = 0;
        B = 0;
        C = 0;


        // Reset de la FSM
        reset = 1;      // Activa el reset
        #10;
        reset = 0;      // Desactiva el reset

        // Esperar un ciclo de reloj
        #30;

        // Probar transición de estado S0 a S1
        A = 1;          // Activa la entrada A para pasar al siguiente estado
        #10;
        A = 0;          // Desactiva la entrada A
        #30;

        // Modificar variable en estado S1
        B = 1;          // Activa la entrada B para modificar la variable del estado S1
        #10;
        B = 0;          // Desactiva la entrada B
        #30;
        B = 1;          // Activa la entrada B para modificar la variable del estado S4
        #10;
        B = 0;          // Desactiva la entrada B
        #30;
         B = 1;          // Activa la entrada B para modificar la variable del estado S4
        #10;
        B = 0;          // Desactiva la entrada B
        #30;
        B = 1;          // Activa la entrada B para modificar la variable del estado S4
        #10;
        B = 0;          // Desactiva la entrada B
        #30;

        // Probar transición de estado S1 a S2
        A = 1;          // Activa la entrada A para pasar al siguiente estado
        #10;
        A = 0;          // Desactiva la entrada A
        #30;

        // Modificar variable en estado S2
        B = 1;          // Activa la entrada B para modificar la variable del estado S2
        #10;
        B = 0;          // Desactiva la entrada B
        #30;

        // Probar transición de estado S2 a S3
        A = 1;          // Activa la entrada A para pasar al siguiente estado
        #10;
        A = 0;          // Desactiva la entrada A
        #30;

        // Modificar variable en estado S3
        B = 1;          // Activa la entrada B para modificar la variable del estado S3
        #10;
        B = 0;          // Desactiva la entrada B
        #30;

        // Probar transición de estado S3 a S4
        A = 1;          // Activa la entrada A para pasar al siguiente estado
        #10;
        A = 0;          // Desactiva la entrada A
        #30;

        // Modificar variable en estado S4
        B = 1;          // Activa la entrada B para modificar la variable del estado S4
        #10;
        B = 0;          // Desactiva la entrada B
        #30;
         B = 1;          // Activa la entrada B para modificar la variable del estado S4
        #10;
        B = 0;          // Desactiva la entrada B
        #30;
         B = 1;          // Activa la entrada B para modificar la variable del estado S4
        #10;
        B = 0;          // Desactiva la entrada B
        #30;

        // Probar transición de estado S4 a S0 (ciclo completo)
        A = 1;          // Activa la entrada A para regresar al estado inicial
        #10;
        A = 0;          // Desactiva la entrada A
        #30;

// Modificar variable en estado S0
        B = 1;          // Activa la entrada B para modificar la variable del estado S4
        #10;
        B = 0;          // Desactiva la entrada B
        #30;
        B = 1;          // Activa la entrada B para modificar la variable del estado S4
        #10;
        B = 0;          // Desactiva la entrada B
        #30;
        B = 1;          // Activa la entrada B para modificar la variable del estado S4
        #10;
        B = 0;          // Desactiva la entrada B
        #30;
        //prueba C
        C = 1;          // Activa la entrada C para regresar en los estados
        #10;
        C = 0;          // Desactiva la entrada C
        #30;
        C = 1;          // Activa la entrada C para regresar en los estados
        #10;
        C = 0;          // Desactiva la entrada C
        #30;
        C = 1;          // Activa la entrada C para regresar en los estados
        #10;
        C = 0;          // Desactiva la entrada C
        #30;
        C = 1;          // Activa la entrada C para regresar en los estados
        #10;
        C = 0;          // Desactiva la entrada C
        #30;
        C = 1;          // Activa la entrada C para regresar en los estados
        #10;
        C = 0;          // Desactiva la entrada C
        #30;                                
        //prueba reset 
        reset = 1;
        #10
        reset = 0;
        #30;
        // Finalización de la simulación
        $stop;
    end
    initial begin: TEST_CASE
        $dumpfile("fsm_mascota_tb.vcd");
        $dumpvars(-1,uut);
        #(1000) $finish;
		
    end


endmodule

FMS/build/fsm_mascota_tb.vcd
$date
	Sun Aug 18 21:23:45 2024
$end
$version
	Icarus Verilog
$end
$timescale
	1ps
$end
$scope module tb_fsm_mascota $end
$scope module uut $end
$var wire 1 ! A $end
$var wire 1 " B $end
$var wire 1 # C $end
$var wire 1 $ clk $end
$var wire 1 % reset $end
$var parameter 32 & S0 $end
$var parameter 32 ' S1 $end
$var parameter 32 ( S2 $end
$var parameter 32 ) S3 $end
$var parameter 32 * S4 $end
$var reg 3 + current_state [0:2] $end
$var reg 3 , next_state [0:2] $end
$var reg 8 - output1 [7:0] $end
$var reg 4 . output2 [3:0] $end
$var reg 4 / var_S0 [3:0] $end
$var reg 4 0 var_S1 [3:0] $end
$var reg 4 1 var_S2 [3:0] $end
$var reg 4 2 var_S3 [3:0] $end
$var reg 4 3 var_S4 [3:0] $end
$upscope $end
$upscope $end
$enddefinitions $end
$comment Show the parameter values. $end
$dumpall
b100 *
b11 )
b10 (
b1 '
b0 &
$end
#0
$dumpvars
b0 3
b0 2
b0 1
b0 0
b0 /
b0 .
b0 -
bx ,
b0 +
1%
0$
0#
0"
0!
$end
#5000
b0 ,
1$
#10000
0$
0%
#15000
1$
#20000
0$
#25000
1$
#30000
0$
#35000
1$
#40000
0$
1!
#45000
b1 .
b1 +
b1 ,
1$
#50000
0$
0!
#55000
1$
#60000
0$
#65000
1$
#70000
0$
#75000
1$
#80000
0$
1"
#85000
b1 -
b1 0
1$
#90000
0$
0"
#95000
1$
#100000
0$
#105000
1$
#110000
0$
#115000
1$
#120000
0$
1"
#125000
b10 -
b10 0
1$
#130000
0$
0"
#135000
1$
#140000
0$
#145000
1$
#150000
0$
#155000
1$
#160000
0$
1"
#165000
b11 -
b11 0
1$
#170000
0$
0"
#175000
1$
#180000
0$
#185000
1$
#190000
0$
#195000
1$
#200000
0$
1"
#205000
b100 -
b100 0
1$
#210000
0$
0"
#215000
1$
#220000
0$
#225000
1$
#230000
0$
#235000
1$
#240000
0$
1!
#245000
b10 .
b0 -
b10 +
b10 ,
1$
#250000
0$
0!
#255000
1$
#260000
0$
#265000
1$
#270000
0$
#275000
1$
#280000
0$
1"
#285000
b1 -
b1 1
1$
#290000
0$
0"
#295000
1$
#300000
0$
#305000
1$
#310000
0$
#315000
1$
#320000
0$
1!
#325000
b11 .
b0 -
b11 +
b11 ,
1$
#330000
0$
0!
#335000
1$
#340000
0$
#345000
1$
#350000
0$
#355000
1$
#360000
0$
1"
#365000
b1 -
b1 2
1$
#370000
0$
0"
#375000
1$
#380000
0$
#385000
1$
#390000
0$
#395000
1$
#400000
0$
1!
#405000
b100 .
b0 -
b100 +
b100 ,
1$
#410000
0$
0!
#415000
1$
#420000
0$
#425000
1$
#430000
0$
#435000
1$
#440000
0$
1"
#445000
b1 -
b1 3
1$
#450000
0$
0"
#455000
1$
#460000
0$
#465000
1$
#470000
0$
#475000
1$
#480000
0$
1"
#485000
b10 -
b10 3
1$
#490000
0$
0"
#495000
1$
#500000
0$
#505000
1$
#510000
0$
#515000
1$
#520000
0$
1"
#525000
b11 -
b11 3
1$
#530000
0$
0"
#535000
1$
#540000
0$
#545000
1$
#550000
0$
#555000
1$
#560000
0$
1!
#565000
b0 .
b0 -
b0 +
b0 ,
1$
#570000
0$
0!
#575000
1$
#580000
0$
#585000
1$
#590000
0$
#595000
1$
#600000
0$
1"
#605000
b1 -
b1 /
1$
#610000
0$
0"
#615000
1$
#620000
0$
#625000
1$
#630000
0$
#635000
1$
#640000
0$
1"
#645000
b10 -
b10 /
1$
#650000
0$
0"
#655000
1$
#660000
0$
#665000
1$
#670000
0$
#675000
1$
#680000
0$
1"
#685000
b11 -
b11 /
1$
#690000
0$
0"
#695000
1$
#700000
0$
#705000
1$
#710000
0$
#715000
1$
#720000
0$
1#
#725000
b100 .
b100 +
b100 ,
1$
#730000
0$
0#
#735000
1$
#740000
0$
#745000
1$
#750000
0$
#755000
1$
#760000
0$
1#
#765000
b11 .
b1 -
b11 +
b11 ,
1$
#770000
0$
0#
#775000
1$
#780000
0$
#785000
1$
#790000
0$
#795000
1$
#800000
0$
1#
#805000
b10 .
b10 +
b10 ,
1$
#810000
0$
0#
#815000
1$
#820000
0$
#825000
1$
#830000
0$
#835000
1$
#840000
0$
1#
#845000
b1 .
b100 -
b1 +
b1 ,
1$
#850000
0$
0#
#855000
1$
#860000
0$
#865000
1$
#870000
0$
#875000
1$
#880000
0$
1#
#885000
b0 .
b11 -
b0 +
b0 ,
1$
#890000
0$
0#
#895000
1$
#900000
0$
#905000
1$
#910000
0$
#915000
1$
#920000
b0 -
b0 3
b0 2
b0 1
b0 0
b0 /
0$
1%
#925000
1$
#930000
0$
0%
